{
  "file_path": "data/sample_resume.txt",
  "text": "John Doe\nSoftware Engineer\nEmail: john.doe@email.com\nPhone: (555) 123-4567\nLinkedIn: linkedin.com/in/johndoe\nGitHub: github.com/johndoe\n\nPROFESSIONAL SUMMARY\nExperienced software engineer with 5 years of experience in full-stack development. \nProficient in Python, JavaScript, and cloud technologies. Strong background in \nbuilding scalable web applications and RESTful APIs.\n\nTECHNICAL SKILLS\nProgramming Languages: Python, JavaScript, TypeScript, Java, SQL\nWeb Technologies: React, Node.js, Express, HTML, CSS\nDatabases: PostgreSQL, MongoDB, Redis\nCloud & DevOps: AWS, Docker, Kubernetes, Jenkins, Git\nFrameworks: Django, Flask, Spring Boot\nTools: Linux, Bash, Vim, VS Code, Jira\n\nPROFESSIONAL EXPERIENCE\n\nSenior Software Engineer - Tech Solutions Inc. (2021 - Present)\n\u2022 Led development of microservices architecture serving 1M+ users\n\u2022 Implemented CI/CD pipelines reducing deployment time by 60%\n\u2022 Mentored junior developers and conducted code reviews\n\u2022 Built RESTful APIs using Python Django and PostgreSQL\n\u2022 Deployed applications on AWS using Docker and Kubernetes\n\nSoftware Engineer - StartupCorp (2019 - 2021)\n\u2022 Developed full-stack web applications using React and Node.js\n\u2022 Optimized database queries improving application performance by 40%\n\u2022 Collaborated with cross-functional teams in Agile environment\n\u2022 Implemented automated testing reducing bugs by 30%\n\nEDUCATION\nBachelor of Science in Computer Science\nUniversity of Technology (2015 - 2019)\nGPA: 3.8/4.0\n\nPROJECTS\nE-commerce Platform\n\u2022 Built scalable e-commerce platform using Python, React, and PostgreSQL\n\u2022 Implemented payment processing and inventory management\n\u2022 Technologies: Python, React, PostgreSQL, AWS, Docker\n\nTask Management API\n\u2022 Developed RESTful API for task management with authentication\n\u2022 Implemented real-time notifications using WebSockets\n\u2022 Technologies: Node.js, Express, MongoDB, Socket.io\n\nCERTIFICATIONS\n\u2022 AWS Certified Solutions Architect - Associate (2022)\n\u2022 Certified Kubernetes Administrator (2021)",
  "analysis": {
    "word_count": 260,
    "sentences": 4,
    "contact_info": {
      "email": "john.doe@email.com",
      "phone": "(555) 123-4567",
      "linkedin": "linkedin.com/in/johndoe",
      "github": "github.com/johndoe",
      "website": null
    },
    "technical_skills": [
      "",
      "spring",
      "css",
      "github",
      "go",
      "docker",
      "javascript",
      ".8",
      "vim",
      "java",
      "flask",
      "bash",
      "python",
      "typescript",
      "react",
      "kubernetes",
      "node.js",
      "sql",
      "jira",
      "scala",
      "postgresql",
      "git",
      "aws",
      "mongodb",
      "r",
      "html",
      "express",
      "django",
      "linux",
      "redis",
      "jenkins"
    ],
    "soft_skills": [],
    "experience_years": 5,
    "education": [
      "Bachelor of Science in Computer Science",
      "University of Technology (2015 - 2019)"
    ],
    "keywords": [
      "python",
      "technology",
      "using",
      "application",
      "aws",
      "engineer",
      "implemented",
      "postgresql",
      "react",
      "software",
      "software engineer",
      "docker",
      "kubernetes",
      "management",
      "restful",
      "web",
      "python javascript",
      "python react",
      "react postgresql",
      "reducing"
    ],
    "sections": [
      "SUMMARY",
      "experience",
      "EDUCATION",
      "TECHNICAL SKILLS",
      "PROJECTS",
      "CERTIFICATIONS"
    ],
    "key_phrases": [
      "software engineer",
      "node js",
      "python javascript",
      "python react",
      "python react postgresql",
      "react node",
      "react node js",
      "react postgresql",
      "restful apis",
      "task management"
    ]
  },
  "analyzed_at": "2025-10-26T22:47:26.401592"
}